Metadata-Version: 2.1
Name: FoxedoKMS
Version: 1.0
Summary: Access your FoxedoKMS Keys with this package.
Home-page: https://github.com/rumeetsingh/foxedo-kms-python
Author: Rumeet Singh
Author-email: singh.rumeet5@gmail.com
License: UNKNOWN
Download-URL: https://github.com/rumeetsingh/foxedo-kms-python/archive/1.0.tar.gz
Platform: UNKNOWN
Classifier: Programming Language :: Python :: 3
Classifier: License :: OSI Approved :: MIT License
Classifier: Operating System :: OS Independent
